piglet/__init__.py
piglet/astutil.py
piglet/compile.py
piglet/compilett.py
piglet/compilexml.py
piglet/exceptions.py
piglet/i18n.py
piglet/intermediate.py
piglet/interpolate.py
piglet/loader.py
piglet/parse.py
piglet/position.py
piglet/runtime.py
piglet/template.py
piglet/test_compilett.py
piglet/test_compilexml.py
piglet/test_i18n.py
piglet/test_interpolate.py
piglet/test_loader.py
piglet/test_parse.py
piglet/test_piglet.py
piglet/test_position.py
piglet/parsers/__init__.py
piglet/parsers/html.py
piglet/parsers/interpolation.py
piglet/parsers/semicolonseparated.py
piglet/parsers/text.py
piglet_templates-1.3.1.dist-info/LICENSE.txt
piglet_templates-1.3.1.dist-info/METADATA
piglet_templates-1.3.1.dist-info/WHEEL
piglet_templates-1.3.1.dist-info/entry_points.txt
piglet_templates-1.3.1.dist-info/top_level.txt
piglet_templates-1.3.1.dist-info/RECORD
