Metadata-Version: 2.1
Name: piglet-templates
Version: 1.3.1
Summary: Fast, robust HTML templating engine
Home-page: https://ollycope.com/software/piglet/latest/
Author: Oliver Cope
Author-email: oliver@redgecko.org
License: Apache
Keywords: jinja2 jinja genshi kajiki mako kid html templating template engine chameleon
Classifier: Development Status :: 5 - Production/Stable
Classifier: Environment :: Web Environment
Classifier: Intended Audience :: Developers
Classifier: License :: OSI Approved :: Apache Software License
Classifier: Operating System :: OS Independent
Classifier: Programming Language :: Python :: 3
Classifier: Programming Language :: Python :: Implementation :: PyPy
Classifier: Topic :: Text Processing
Classifier: Topic :: Text Processing :: Markup :: HTML
Classifier: Topic :: Internet :: WWW/HTTP :: Dynamic Content
License-File: LICENSE.txt
